numaprom/__init__.py
numaprom/monitoring/__init__.py
numaprom/monitoring/config.py
numaprom/monitoring/metrics.py
numaprom/monitoring/utility.py
numalogic_prometheus-0.8.0.dist-info/LICENSE
numalogic_prometheus-0.8.0.dist-info/METADATA
numalogic_prometheus-0.8.0.dist-info/WHEEL
numalogic_prometheus-0.8.0.dist-info/RECORD
